rtl/branch_comparator.v
`timescale 1ns/1ps

module branch_comparator(

    input [31:0] rs1_data,
    input [31:0] rs2_data,

    output branch_taken

);

assign branch_taken = (rs1_data == rs2_data);

endmodule

rtl/data_memory.v
`timescale 1ns/1ps

module data_memory(

    input clk,
    input mem_write,
    input mem_read,
    input [31:0] address,
    input [31:0] write_data,

    output reg [31:0] read_data

);

reg [31:0] memory [0:255];

// Read (Combinational)
always @(*) begin
    if (mem_read)
        read_data = memory[address[31:2]];
    else
        read_data = 32'd0;
end

// Write (Synchronous)
always @(posedge clk) begin
    if (mem_write)
        memory[address[31:2]] <= write_data;
end

endmodule

rtl/alu.v
module alu (
    input  [31:0] a,
    input  [31:0] b,
    input  [3:0] alu_control,

    output reg [31:0] result,
    output zero
);

always @(*) begin
    case (alu_control)

        4'b0000: result = a + b;                         // ADD

        4'b0001: result = a - b;                         // SUB

        4'b0010: result = a & b;                         // AND

        4'b0011: result = a | b;                         // OR

        4'b0100: result = a ^ b;                         // XOR

        4'b0101: result = a << b[4:0];                   // SLL

        4'b0110: result = a >> b[4:0];                   // SRL

        4'b0111: result = ($signed(a) < $signed(b))
                            ? 32'd1
                            : 32'd0;                     // SLT

        4'b1000: result = $signed(a) >>> b[4:0];         // SRA

        default: result = 32'd0;

    endcase
end

assign zero = (result == 32'd0);

endmodule

rtl/alu_control.v
`timescale 1ns/1ps

module alu_control(

    input [1:0] ALUOp,
    input [2:0] funct3,
    input [6:0] funct7,

    output reg [3:0] ALUCtrl

);

always @(*) begin

    case(ALUOp)

        // Load / Store
        2'b00:
            ALUCtrl = 4'b0000;   // ADD

        // Branch
        2'b01:
            ALUCtrl = 4'b0001;   // SUB

        // R-Type / I-Type
        2'b10: begin

            case(funct3)

                3'b000:
                    if(funct7 == 7'b0100000)
                        ALUCtrl = 4'b0001;    // SUB
                    else
                        ALUCtrl = 4'b0000;    // ADD

                3'b111:
                    ALUCtrl = 4'b0010;        // AND

                3'b110:
                    ALUCtrl = 4'b0011;        // OR

                3'b100:
                    ALUCtrl = 4'b0100;        // XOR

                3'b001:
                    ALUCtrl = 4'b0101;        // SLL

                3'b101:
                    ALUCtrl = 4'b0110;        // SRL

                3'b010:
                    ALUCtrl = 4'b0111;        // SLT

                default:
                    ALUCtrl = 4'b0000;

            endcase

        end

        default:
            ALUCtrl = 4'b0000;

    endcase

end

endmodule

rtl/register_file.v
module register_file(

    input clk,
    input we,
    input reset,

    input [4:0] rs1,
    input [4:0] rs2,
    input [4:0] rd,

    input [31:0] write_data,

    output [31:0] read_data1,
    output [31:0] read_data2

);

reg [31:0] registers [0:31];

// Write-first bypass: if WB is writing the same register we're reading
// this cycle, forward the write data instead of the stale array value.
// (Needed because, in the pipeline, ID reads and WB writes happen on
// the same clock edge for a register file modeled with a single array.)
assign read_data1 = (rs1 == 5'd0) ? 32'd0 :
                     (we && rd == rs1 && rd != 5'd0) ? write_data :
                     registers[rs1];

assign read_data2 = (rs2 == 5'd0) ? 32'd0 :
                     (we && rd == rs2 && rd != 5'd0) ? write_data :
                     registers[rs2];

integer i;

always @(posedge clk or posedge reset) begin
    if (reset) begin
        for (i = 0; i < 32; i = i + 1)
            registers[i] <= 32'd0;
    end
    else if (we && (rd != 5'd0)) begin
        registers[rd] <= write_data;
    end
end

endmodule

rtl/immediate_generator.v
`timescale 1ns/1ps

module immediate_generator(

    input  [31:0] instruction,
    output reg [31:0] immediate

);

wire [6:0] opcode = instruction[6:0];

always @(*) begin

    case(opcode)

        // I-Type
        7'b0010011,
        7'b0000011:
            immediate = {{20{instruction[31]}}, instruction[31:20]};

        // S-Type
        7'b0100011:
            immediate = {{20{instruction[31]}},
                         instruction[31:25],
                         instruction[11:7]};

        // B-Type
        7'b1100011:
            immediate = {{19{instruction[31]}},
                         instruction[31],
                         instruction[7],
                         instruction[30:25],
                         instruction[11:8],
                         1'b0};

        // U-Type
        7'b0110111,
        7'b0010111:
            immediate = {instruction[31:12],12'b0};

        // J-Type
        7'b1101111:
            immediate = {{11{instruction[31]}},
                         instruction[31],
                         instruction[19:12],
                         instruction[20],
                         instruction[30:21],
                         1'b0};

        default:
            immediate = 32'd0;

    endcase

end

endmodule

rtl/control_unit.v
`timescale 1ns/1ps

module control_unit(

    input [6:0] opcode,

    output reg RegWrite,
    output reg ALUSrc,
    output reg MemRead,
    output reg MemWrite,
    output reg MemtoReg,
    output reg Branch,
    output reg Jump,
    output reg [1:0] ALUOp

);

always @(*) begin

    // Defaults
    RegWrite = 0;
    ALUSrc   = 0;
    MemRead  = 0;
    MemWrite = 0;
    MemtoReg = 0;
    Branch   = 0;
    Jump     = 0;
    ALUOp    = 2'b00;

    case(opcode)

        // R-Type
        7'b0110011: begin
            RegWrite = 1;
            ALUOp    = 2'b10;
        end

        // I-Type
        7'b0010011: begin
            RegWrite = 1;
            ALUSrc   = 1;
            ALUOp    = 2'b10;
        end

        // Load
        7'b0000011: begin
            RegWrite = 1;
            ALUSrc   = 1;
            MemRead  = 1;
            MemtoReg = 1;
            ALUOp    = 2'b00;
        end

        // Store
        7'b0100011: begin
            ALUSrc   = 1;
            MemWrite = 1;
            ALUOp    = 2'b00;
        end

        // Branch
        7'b1100011: begin
            Branch = 1;
            ALUOp  = 2'b01;
        end

        // JAL
        7'b1101111: begin
            Jump     = 1;
            RegWrite = 1;
        end

        // LUI
        7'b0110111: begin
            RegWrite = 1;
            ALUSrc   = 1;
        end

    endcase

end

endmodule

rtl/instruction_memory.v
`timescale 1ns/1ps

module instruction_memory(

    input  [31:0] pc,
    output [31:0] instruction

);

reg [31:0] memory [0:255];

// Small test program
initial begin
    memory[0] = 32'h008000EF; // jal x1, +8
    memory[1] = 32'h00100113; // addi x2, x0, 1 (should be skipped)
    memory[2] = 32'h06300193; // addi x3, x0, 99
end

assign instruction = memory[pc[31:2]];

endmodule

rtl/program_counter.v
`timescale 1ns/1ps

module program_counter(

    input clk,
    input reset,
    input [31:0] next_pc,

    output reg [31:0] pc

);

always @(posedge clk or posedge reset) begin
    if(reset)
        pc <= 32'd0;
    else
        pc <= next_pc;
end

endmodule

rtl/cpu.v
`timescale 1ns/1ps

module cpu(

    input clk,
    input reset

);

// Program Counter
wire [31:0] pc;
wire [31:0] next_pc;
wire [31:0] pc_plus_4;
wire [31:0] branch_target;

// Instruction
wire [31:0] instruction;

// Register File
wire [31:0] read_data1;
wire [31:0] read_data2;

// Immediate
wire [31:0] immediate;

// ALU
wire [31:0] alu_result;
wire zero;

// Memory
wire [31:0] memory_data;
wire [31:0] write_back_data;


// Branch
wire branch_taken;

// Control
wire RegWrite;
wire ALUSrc;
wire MemRead;
wire MemWrite;
wire MemtoReg;
wire Branch;
wire Jump;
wire [1:0] ALUOp;

// ALU Control
wire [3:0] ALUCtrl;
wire [31:0] alu_input_b;

assign alu_input_b   = ALUSrc ? immediate : read_data2;
assign write_back_data = MemtoReg ? memory_data : alu_result;
assign pc_plus_4     = pc + 4;
assign branch_target = pc + immediate;
assign next_pc = (Branch && branch_taken) ? branch_target : pc_plus_4;
program_counter pc_unit(

    .clk(clk),
    .reset(reset),
    .next_pc(next_pc),
    .pc(pc)

);

instruction_memory imem(

    .pc(pc),
    .instruction(instruction)

);

control_unit control(

    .opcode(instruction[6:0]),

    .RegWrite(RegWrite),
    .ALUSrc(ALUSrc),
    .MemRead(MemRead),
    .MemWrite(MemWrite),
    .MemtoReg(MemtoReg),
    .Branch(Branch),
    .Jump(Jump),
    .ALUOp(ALUOp)

);

immediate_generator imm_gen(

    .instruction(instruction),
    .immediate(immediate)

);

register_file rf(

    .clk(clk),
    .reset(reset),
    .we(RegWrite),

    .rs1(instruction[19:15]),
    .rs2(instruction[24:20]),
    .rd(instruction[11:7]),

    .write_data(write_back_data),

    .read_data1(read_data1),
    .read_data2(read_data2)

);

alu_control alu_ctrl(

    .ALUOp(ALUOp),
    .funct3(instruction[14:12]),
    .funct7(instruction[31:25]),

    .ALUCtrl(ALUCtrl)

);


alu alu_unit(

    .a(read_data1),
    .b(alu_input_b),
    .alu_control(ALUCtrl),

    .result(alu_result),
    .zero(zero)

);



data_memory dmem(

    .clk(clk),
    .mem_write(MemWrite),
    .mem_read(MemRead),

    .address(alu_result),
    .write_data(read_data2),

    .read_data(memory_data)

);


branch_comparator branch_cmp(

    .rs1_data(read_data1),
    .rs2_data(read_data2),

    .branch_taken(branch_taken)

);



endmodule

testbench/cpu_tb.v
`timescale 1ns/1ps

module cpu_tb;

reg clk;
reg reset;

cpu uut(
    .clk(clk),
    .reset(reset)
);

// Clock
// Clock
always #5 clk = ~clk;

initial begin
    $dumpfile("cpu.vcd");
    $dumpvars(0, cpu_tb);

    clk = 0;
    reset = 1;

    #10;
    reset = 0;

    #100;

    

    $display("x1 = %d", uut.rf.registers[1]);
    $display("x2 = %d", uut.rf.registers[2]);
    $display("x3 = %d", uut.rf.registers[3]);

$finish;
end

endmodule

cpu.vcd
$date
	Wed Jul 22 17:39:49 2026
$end
$version
	Icarus Verilog
$end
$timescale
	1ps
$end
$scope module cpu_tb $end
$var reg 1 ! clk $end
$var reg 1 " reset $end
$scope module uut $end
$var wire 1 ! clk $end
$var wire 1 " reset $end
$var wire 1 # zero $end
$var wire 32 $ write_back_data [31:0] $end
$var wire 32 % read_data2 [31:0] $end
$var wire 32 & read_data1 [31:0] $end
$var wire 32 ' pc_plus_4 [31:0] $end
$var wire 32 ( pc [31:0] $end
$var wire 32 ) next_pc [31:0] $end
$var wire 32 * memory_data [31:0] $end
$var wire 32 + instruction [31:0] $end
$var wire 32 , immediate [31:0] $end
$var wire 32 - branch_target [31:0] $end
$var wire 1 . branch_taken $end
$var wire 32 / alu_result [31:0] $end
$var wire 32 0 alu_input_b [31:0] $end
$var wire 1 1 RegWrite $end
$var wire 1 2 MemtoReg $end
$var wire 1 3 MemWrite $end
$var wire 1 4 MemRead $end
$var wire 1 5 Jump $end
$var wire 1 6 Branch $end
$var wire 1 7 ALUSrc $end
$var wire 2 8 ALUOp [1:0] $end
$var wire 4 9 ALUCtrl [3:0] $end
$scope module alu_ctrl $end
$var wire 3 : funct3 [2:0] $end
$var wire 7 ; funct7 [6:0] $end
$var wire 2 < ALUOp [1:0] $end
$var reg 4 = ALUCtrl [3:0] $end
$upscope $end
$scope module alu_unit $end
$var wire 4 > alu_control [3:0] $end
$var wire 32 ? b [31:0] $end
$var wire 1 # zero $end
$var wire 32 @ a [31:0] $end
$var reg 32 A result [31:0] $end
$upscope $end
$scope module branch_cmp $end
$var wire 32 B rs2_data [31:0] $end
$var wire 32 C rs1_data [31:0] $end
$var wire 1 . branch_taken $end
$upscope $end
$scope module control $end
$var wire 7 D opcode [6:0] $end
$var reg 2 E ALUOp [1:0] $end
$var reg 1 7 ALUSrc $end
$var reg 1 6 Branch $end
$var reg 1 5 Jump $end
$var reg 1 4 MemRead $end
$var reg 1 3 MemWrite $end
$var reg 1 2 MemtoReg $end
$var reg 1 1 RegWrite $end
$upscope $end
$scope module dmem $end
$var wire 32 F address [31:0] $end
$var wire 1 ! clk $end
$var wire 1 4 mem_read $end
$var wire 1 3 mem_write $end
$var wire 32 G write_data [31:0] $end
$var reg 32 H read_data [31:0] $end
$upscope $end
$scope module imem $end
$var wire 32 I instruction [31:0] $end
$var wire 32 J pc [31:0] $end
$upscope $end
$scope module imm_gen $end
$var wire 32 K instruction [31:0] $end
$var wire 7 L opcode [6:0] $end
$var reg 32 M immediate [31:0] $end
$upscope $end
$scope module pc_unit $end
$var wire 1 ! clk $end
$var wire 32 N next_pc [31:0] $end
$var wire 1 " reset $end
$var reg 32 O pc [31:0] $end
$upscope $end
$scope module rf $end
$var wire 1 ! clk $end
$var wire 5 P rd [4:0] $end
$var wire 1 " reset $end
$var wire 5 Q rs1 [4:0] $end
$var wire 5 R rs2 [4:0] $end
$var wire 1 1 we $end
$var wire 32 S write_data [31:0] $end
$var wire 32 T read_data2 [31:0] $end
$var wire 32 U read_data1 [31:0] $end
$var integer 32 V i [31:0] $end
$upscope $end
$upscope $end
$upscope $end
$enddefinitions $end
$comment Show the parameter values. $end
$dumpall
$end
#0
$dumpvars
b100000 V
b0 U
b0 T
b100 S
b1000 R
b0 Q
b1 P
b0 O
b1000 N
b1000 M
b1101111 L
b100000000000000011101111 K
b0 J
b100000000000000011101111 I
b0 H
b0 G
b0 F
b0 E
b1101111 D
b0 C
b0 B
b0 A
b0 @
b0 ?
b0 >
b0 =
b0 <
b0 ;
b0 :
b0 9
b0 8
07
06
15
04
03
02
11
b0 0
b0 /
1.
b1000 -
b1000 ,
b100000000000000011101111 +
b0 *
b1000 )
b0 (
b100 '
b0 &
b0 %
b100 $
1#
1"
0!
$end
#5000
b100000 V
1!
#10000
0!
0"
#15000
0#
b1100011 /
b1100011 A
b1100011 F
b1100011 0
b1100011 ?
b10 8
b10 <
b10 E
17
05
11
b1100011 ,
b1100011 M
b10011 L
b11 ;
b11 P
b11 R
b10011 D
b110001100000000000110010011 +
b110001100000000000110010011 I
b110001100000000000110010011 K
b1100 )
b1100 N
b1100011 $
b1100011 S
b1101011 -
b1100 '
b1000 (
b1000 J
b1000 O
1!
#20000
0!
#25000
bx $
bx S
x#
bx /
bx A
bx F
bx 0
bx ?
bx &
bx @
bx C
bx U
b0 8
b0 <
b0 E
07
01
b0 ,
b0 M
bx L
bx ;
bx :
bx P
bx R
bx Q
bx D
b10000 )
b10000 N
x.
bx %
bx B
bx G
bx T
bx +
bx I
bx K
b1100 -
b10000 '
b1100 (
b1100 J
b1100 O
1!
#30000
0!
#35000
b10100 )
b10100 N
b10000 -
b10100 '
b10000 (
b10000 J
b10000 O
1!
#40000
0!
#45000
b11000 )
b11000 N
b10100 -
b11000 '
b10100 (
b10100 J
b10100 O
1!
#50000
0!
#55000
b11100 )
b11100 N
b11000 -
b11100 '
b11000 (
b11000 J
b11000 O
1!
#60000
0!
#65000
b100000 )
b100000 N
b11100 -
b100000 '
b11100 (
b11100 J
b11100 O
1!
#70000
0!
#75000
b100100 )
b100100 N
b100000 -
b100100 '
b100000 (
b100000 J
b100000 O
1!
#80000
0!
#85000
b101000 )
b101000 N
b100100 -
b101000 '
b100100 (
b100100 J
b100100 O
1!
#90000
0!
#95000
b101100 )
b101100 N
b101000 -
b101100 '
b101000 (
b101000 J
b101000 O
1!
#100000
0!
#105000
b110000 )
b110000 N
b101100 -
b110000 '
b101100 (
b101100 J
b101100 O
1!
